{
    "name": "The Word for World Is Forest", 
    "author": "Ursula K. Le Guin", 
    "year_read": "2022", 
    "month_read": "7", 
    "recommended_by": "Theo", 
    "genre": ["science fiction"], 
    "book_description": "When the inhabitants of a peaceful world are conquered by the bloodthirsty yumens, their existence is irrevocably altered. Forced into servitude, the Athsheans find themselves at the mercy of their brutal masters. Desperation causes the Athsheans, led by Selver, to retaliate against their captors, abandoning their strictures against violence. But in defending their lives, they have endangered the very foundations of their society. For every blow against the invaders is a blow to the humanity of the Athsheans. And once the killing starts, there is no turning back. At the publisher's request, this title is being sold without Digital Rights Management software (DRM) applied.", 
    "club_thoughts": "", 
    "cover": "20.jpg"
}